{
  "@context": [
    "https://www.w3.org/ns/did/v1",
    "https://w3id.org/security/multikey/v1",
    {
      "@vocab": "https://to-be-replaced-vocab.com#"
    },
    "https://w3id.org/security/data-integrity/v2"
  ],
  "id": "did:best:1vqtjq6g3uzj2yvk7t3hkzeeo",
  "authentication": [
    "did:best:1vqtjq6g3uzj2yvk7t3hkzeeo#CXB47qep"
  ],
  "assertionMethod": [
    "did:best:1vqtjq6g3uzj2yvk7t3hkzeeo#wKsQqFCx"
  ],
  "verificationMethod": [
    {
      "id": "did:best:1vqtjq6g3uzj2yvk7t3hkzeeo#CXB47qep",
      "controller": "did:best:1vqtjq6g3uzj2yvk7t3hkzeeo",
      "type": "Multikey",
      "publicKeyMultibase": "z6Mkss7jY2KBxcmBAYoEj7qkNs5CHy5ZsmynbvHLCXB47qep"
    },
    {
      "id": "did:best:1vqtjq6g3uzj2yvk7t3hkzeeo#wKsQqFCx",
      "controller": "did:best:1vqtjq6g3uzj2yvk7t3hkzeeo",
      "type": "Multikey",
      "publicKeyMultibase": "z6Mkknzxr3ttTXm1zvPhyeYgFgCLBD99bGreenpkwKsQqFCx"
    }
  ],
  "versionId": 19,
  "previousHash": "baga6yaqsebnweauygfeck4cxcefda6gr2sfvrohscapamlvsgm6dgdq2lopx4",
  "proof": {
    "type": "DataIntegrityProof",
    "created": "2024-03-19T17:58:34Z",
    "verificationMethod": "did:best:1vqtjq6g3uzj2yvk7t3hkzeeo#CXB47qep",
    "cryptosuite": "eddsa-2022",
    "proofPurpose": "authentication",
    "challenge": "baga6yaqsebnweauygfeck4cxcefda6gr2sfvrohscapamlvsgm6dgdq2lopx4",
    "proofValue": "z5oA2vyizgd564WFiVb1pA3GNBaqKDZvexhj4bZaF5kYJGNjNR6bKZK19K3XofjDxD7q1NzZDjz1vQTF3oxe4VoKK"
  }
}